{
  "url": "https://www.upgradabroad.com/university/australia/edith-cowan-university-40",
  "unique_key": "https://www.upgradabroad.com/university/australia/edith-cowan-university-40",
  "method": "GET",
  "headers": {},
  "payload": null,
  "user_data": {
    "__crawlee": {
      "crawlDepth": 1
    }
  },
  "retry_count": 0,
  "no_retry": false,
  "loaded_url": null,
  "handled_at": null,
  "id": "Gvj1HuFz8Ao6e8C",
  "json_": "{\n  \"url\": \"https://www.upgradabroad.com/university/australia/edith-cowan-university-40\",\n  \"unique_key\": \"https://www.upgradabroad.com/university/australia/edith-cowan-university-40\",\n  \"method\": \"GET\",\n  \"headers\": {},\n  \"payload\": null,\n  \"user_data\": {\n    \"__crawlee\": {\n      \"crawlDepth\": 1\n    }\n  },\n  \"retry_count\": 0,\n  \"no_retry\": false,\n  \"loaded_url\": null,\n  \"handled_at\": null,\n  \"id\": \"Gvj1HuFz8Ao6e8C\",\n  \"order_no\": \"1731746818968.425989\"\n}",
  "order_no": "1731746818968.425989"
}