{
  "url": "https://www.seek.com.au/job/79725236?type=promoted&ref=search-standalone#sol=e66c47ab49ba954f665da187dc3799d0f862c6dd",
  "unique_key": "https://www.seek.com.au/job/79725236?ref=search-standalone&type=promoted",
  "method": "GET",
  "headers": {},
  "payload": null,
  "user_data": {
    "__crawlee": {
      "crawlDepth": 1
    }
  },
  "retry_count": 0,
  "no_retry": false,
  "loaded_url": null,
  "handled_at": null,
  "id": "jgB8ygbqZf4zmfr",
  "json_": "{\n  \"url\": \"https://www.seek.com.au/job/79725236?type=promoted&ref=search-standalone#sol=e66c47ab49ba954f665da187dc3799d0f862c6dd\",\n  \"unique_key\": \"https://www.seek.com.au/job/79725236?ref=search-standalone&type=promoted\",\n  \"method\": \"GET\",\n  \"headers\": {},\n  \"payload\": null,\n  \"user_data\": {\n    \"__crawlee\": {\n      \"crawlDepth\": 1\n    }\n  },\n  \"retry_count\": 0,\n  \"no_retry\": false,\n  \"loaded_url\": null,\n  \"handled_at\": null,\n  \"id\": \"jgB8ygbqZf4zmfr\",\n  \"order_no\": \"1731746769270.515919\"\n}",
  "order_no": "1731746769270.515919"
}