{
  "url": "https://www.upgradabroad.com/university/canada/memorial-university-of-newfoundland-700",
  "unique_key": "https://www.upgradabroad.com/university/canada/memorial-university-of-newfoundland-700",
  "method": "GET",
  "headers": {},
  "payload": null,
  "user_data": {
    "__crawlee": {
      "crawlDepth": 1
    }
  },
  "retry_count": 0,
  "no_retry": false,
  "loaded_url": null,
  "handled_at": null,
  "id": "kC41mJKGR0cMiZJ",
  "json_": "{\n  \"url\": \"https://www.upgradabroad.com/university/canada/memorial-university-of-newfoundland-700\",\n  \"unique_key\": \"https://www.upgradabroad.com/university/canada/memorial-university-of-newfoundland-700\",\n  \"method\": \"GET\",\n  \"headers\": {},\n  \"payload\": null,\n  \"user_data\": {\n    \"__crawlee\": {\n      \"crawlDepth\": 1\n    }\n  },\n  \"retry_count\": 0,\n  \"no_retry\": false,\n  \"loaded_url\": null,\n  \"handled_at\": null,\n  \"id\": \"kC41mJKGR0cMiZJ\",\n  \"order_no\": \"1731746819203.835011\"\n}",
  "order_no": "1731746819203.835011"
}