{
  "url": "https://www.seek.com.au/FDM-Group-jobs",
  "unique_key": "https://www.seek.com.au/fdm-group-jobs",
  "method": "GET",
  "headers": {},
  "payload": null,
  "user_data": {
    "__crawlee": {
      "crawlDepth": 1
    }
  },
  "retry_count": 0,
  "no_retry": false,
  "loaded_url": null,
  "handled_at": null,
  "id": "pGs5HGu9OToA8sI",
  "json_": "{\n  \"url\": \"https://www.seek.com.au/FDM-Group-jobs\",\n  \"unique_key\": \"https://www.seek.com.au/fdm-group-jobs\",\n  \"method\": \"GET\",\n  \"headers\": {},\n  \"payload\": null,\n  \"user_data\": {\n    \"__crawlee\": {\n      \"crawlDepth\": 1\n    }\n  },\n  \"retry_count\": 0,\n  \"no_retry\": false,\n  \"loaded_url\": null,\n  \"handled_at\": null,\n  \"id\": \"pGs5HGu9OToA8sI\",\n  \"order_no\": \"1731746769486.507893\"\n}",
  "order_no": "1731746769486.507893"
}