{
  "url": "https://www.upgradabroad.com/abroad/bachelors/bsc-nursing",
  "unique_key": "https://www.upgradabroad.com/abroad/bachelors/bsc-nursing",
  "method": "GET",
  "headers": {},
  "payload": null,
  "user_data": {
    "__crawlee": {
      "crawlDepth": 1
    }
  },
  "retry_count": 0,
  "no_retry": false,
  "loaded_url": null,
  "handled_at": null,
  "id": "YJLqZSVXH3c5YOV",
  "json_": "{\n  \"url\": \"https://www.upgradabroad.com/abroad/bachelors/bsc-nursing\",\n  \"unique_key\": \"https://www.upgradabroad.com/abroad/bachelors/bsc-nursing\",\n  \"method\": \"GET\",\n  \"headers\": {},\n  \"payload\": null,\n  \"user_data\": {\n    \"__crawlee\": {\n      \"crawlDepth\": 1\n    }\n  },\n  \"retry_count\": 0,\n  \"no_retry\": false,\n  \"loaded_url\": null,\n  \"handled_at\": null,\n  \"id\": \"YJLqZSVXH3c5YOV\",\n  \"order_no\": \"1731746820320.473909\"\n}",
  "order_no": "1731746820320.473909"
}